python_observer/__init__.py
python_observer/cli.py
python_observer/constants.py
python_observer/date.py
python_observer/display.py
python_observer/misc.py
python_observer/watch.py
python_observer-0.3.2.dist-info/entry_points.txt
python_observer-0.3.2.dist-info/LICENSE
python_observer-0.3.2.dist-info/METADATA
python_observer-0.3.2.dist-info/WHEEL
python_observer-0.3.2.dist-info/RECORD
