Metadata-Version: 2.1
Name: python-observer
Version: 0.3.2
Summary: Live reload for Python apps
License: MIT
Author: Skyascii
Author-email: savioxavier112@gmail.com
Requires-Python: >=3.8,<4.0
Classifier: License :: OSI Approved :: MIT License
Classifier: Programming Language :: Python :: 3
Classifier: Programming Language :: Python :: 3.8
Classifier: Programming Language :: Python :: 3.9
Classifier: Programming Language :: Python :: 3.10
Classifier: Programming Language :: Python :: 3.11
Requires-Dist: humanfriendly (>=10.0,<11.0)
Requires-Dist: pyboxen (>=1.2.0,<2.0.0)
Requires-Dist: rich (>=12.5.1)
